richpride/__init__.py
richpride-0.1.5.dist-info/LICENSE
richpride-0.1.5.dist-info/METADATA
richpride-0.1.5.dist-info/WHEEL
richpride-0.1.5.dist-info/top_level.txt
richpride-0.1.5.dist-info/RECORD
