Metadata-Version: 2.2
Name: richpride
Version: 0.1.5
Summary: A collection of pride flag emojis for use with the Rich library.
Author-email: SafeyX3 <bytesarecool@gmail.com>
License: MIT License
Project-URL: Homepage, https://github.com/pypa/richpride
Project-URL: Issues, https://github.com/pypa/richpride/issues
Classifier: Programming Language :: Python :: 3
Classifier: Operating System :: OS Independent
Classifier: License :: OSI Approved :: MIT License
Requires-Python: >=3.6
License-File: LICENSE
Requires-Dist: rich>=10.0
